poetry_plugin_multiverse/__init__.py
poetry_plugin_multiverse/cli/__init__.py
poetry_plugin_multiverse/cli/progress.py
poetry_plugin_multiverse/cli/status.py
poetry_plugin_multiverse/cli/utils.py
poetry_plugin_multiverse/commands/__init__.py
poetry_plugin_multiverse/commands/check.py
poetry_plugin_multiverse/commands/info.py
poetry_plugin_multiverse/commands/lock.py
poetry_plugin_multiverse/commands/run.py
poetry_plugin_multiverse/commands/show.py
poetry_plugin_multiverse/commands/workspace.py
poetry_plugin_multiverse/compatibility/__init__.py
poetry_plugin_multiverse/compatibility/factory.py
poetry_plugin_multiverse/config.py
poetry_plugin_multiverse/dependencies.py
poetry_plugin_multiverse/errors.py
poetry_plugin_multiverse/hooks/__init__.py
poetry_plugin_multiverse/hooks/build.py
poetry_plugin_multiverse/hooks/hook.py
poetry_plugin_multiverse/hooks/lock.py
poetry_plugin_multiverse/packages.py
poetry_plugin_multiverse/plugin.py
poetry_plugin_multiverse/publish.py
poetry_plugin_multiverse/py.typed
poetry_plugin_multiverse/repositories.py
poetry_plugin_multiverse/root.py
poetry_plugin_multiverse/utils.py
poetry_plugin_multiverse/workspace.py
poetry_plugin_multiverse-0.4.3.dist-info/METADATA
poetry_plugin_multiverse-0.4.3.dist-info/WHEEL
poetry_plugin_multiverse-0.4.3.dist-info/entry_points.txt
poetry_plugin_multiverse-0.4.3.dist-info/licenses/LICENSE.txt
poetry_plugin_multiverse-0.4.3.dist-info/RECORD
